attention_viz/__init__.py
attention_viz/core.py
attention_viz/utils.py
attention_viz/version.py
attention_viz/dashboard/__init__.py
attention_viz/dashboard/app.py
attention_viz/extractors/__init__.py
attention_viz/extractors/base.py
attention_viz/extractors/model_adapters.py
attention_viz/visualizers/__init__.py
attention_viz/visualizers/comparison.py
attention_viz/visualizers/evolution.py
attention_viz/visualizers/flow.py
attention_viz/visualizers/heatmap.py
tests/__init__.py
tests/conftest.py
tests/test_basic.py
transformers_attention_viz-0.1.15.dist-info/licenses/LICENSE
transformers_attention_viz-0.1.15.dist-info/METADATA
transformers_attention_viz-0.1.15.dist-info/WHEEL
transformers_attention_viz-0.1.15.dist-info/entry_points.txt
transformers_attention_viz-0.1.15.dist-info/top_level.txt
transformers_attention_viz-0.1.15.dist-info/RECORD
